odoo/addons/base_custom_info/README.rst
odoo/addons/base_custom_info/__init__.py
odoo/addons/base_custom_info/__manifest__.py
odoo/addons/base_custom_info/demo/custom.info.category.csv
odoo/addons/base_custom_info/demo/custom.info.option.csv
odoo/addons/base_custom_info/demo/custom.info.property.csv
odoo/addons/base_custom_info/demo/custom.info.template.csv
odoo/addons/base_custom_info/demo/defaults.xml
odoo/addons/base_custom_info/demo/res_groups.xml
odoo/addons/base_custom_info/i18n/am.po
odoo/addons/base_custom_info/i18n/base_custom_info.pot
odoo/addons/base_custom_info/i18n/ca.po
odoo/addons/base_custom_info/i18n/de.po
odoo/addons/base_custom_info/i18n/el_GR.po
odoo/addons/base_custom_info/i18n/es.po
odoo/addons/base_custom_info/i18n/es_AR.po
odoo/addons/base_custom_info/i18n/es_ES.po
odoo/addons/base_custom_info/i18n/fi.po
odoo/addons/base_custom_info/i18n/fr.po
odoo/addons/base_custom_info/i18n/fr_CA.po
odoo/addons/base_custom_info/i18n/gl.po
odoo/addons/base_custom_info/i18n/hr.po
odoo/addons/base_custom_info/i18n/hr_HR.po
odoo/addons/base_custom_info/i18n/it.po
odoo/addons/base_custom_info/i18n/nl.po
odoo/addons/base_custom_info/i18n/pt.po
odoo/addons/base_custom_info/i18n/pt_BR.po
odoo/addons/base_custom_info/i18n/pt_PT.po
odoo/addons/base_custom_info/i18n/ru.po
odoo/addons/base_custom_info/i18n/sl.po
odoo/addons/base_custom_info/i18n/tr.po
odoo/addons/base_custom_info/i18n/zh_CN.po
odoo/addons/base_custom_info/images/customizations-everywhere.jpg
odoo/addons/base_custom_info/images/menu.png
odoo/addons/base_custom_info/images/properties.png
odoo/addons/base_custom_info/images/templateception.jpg
odoo/addons/base_custom_info/images/templates.png
odoo/addons/base_custom_info/images/values.png
odoo/addons/base_custom_info/models/__init__.py
odoo/addons/base_custom_info/models/custom_info.py
odoo/addons/base_custom_info/models/custom_info_category.py
odoo/addons/base_custom_info/models/custom_info_option.py
odoo14_addon_base_custom_info-14.0.1.0.3.dist-info/METADATA
odoo14_addon_base_custom_info-14.0.1.0.3.dist-info/WHEEL
odoo14_addon_base_custom_info-14.0.1.0.3.dist-info/top_level.txt
odoo14_addon_base_custom_info-14.0.1.0.3.dist-info/RECORD
